monei/__init__.py
monei/client.py
monei/exceptions.py
monei/models/__init__.py
monei/models/agent.py
monei/models/base.py
monei/models/beneficiaries.py
monei/models/bills.py
monei/models/evm.py
monei/models/exchange.py
monei/models/settings.py
monei/models/solana.py
monei/models/transactions.py
monei/models/user.py
monei/models/wallet.py
monei/services/__init__.py
monei/services/agent_service.py
monei/services/beneficiary_service.py
monei/services/bill_service.py
monei/services/evm_service.py
monei/services/exchange_service.py
monei/services/solana_service.py
monei/services/transaction_service.py
monei/services/user_service.py
monei/services/wallet_service.py
monei_sdk-0.1.1.dist-info/licenses/LICENSE
monei_sdk-0.1.1.dist-info/METADATA
monei_sdk-0.1.1.dist-info/WHEEL
monei_sdk-0.1.1.dist-info/top_level.txt
monei_sdk-0.1.1.dist-info/RECORD
