Metadata-Version: 2.4
Name: monei-sdk
Version: 0.1.1
Summary: Official Python SDK for Monei API - AI agent for finance, Financial services, wallets, and crypto exchange
Home-page: https://github.com/Mr-Money01/monei-python-sdk
Author: Monei Team
Author-email: Monei Team <tech@monei.cc>
License: MIT
Project-URL: Homepage, https://monei.cc
Project-URL: Documentation, https://api.monei.cc/api-gateway-docs/
Project-URL: Repository, https://github.com/Mr-Money01/monei-python-sdk.git
Project-URL: Issues, https://github.com/monei/monei-python-sdk/issues
Keywords: monei,api,sdk,payments,crypto,wallet,blockchain
Classifier: Development Status :: 4 - Beta
Classifier: Intended Audience :: Developers
Classifier: License :: OSI Approved :: MIT License
Classifier: Operating System :: OS Independent
Classifier: Programming Language :: Python :: 3
Classifier: Programming Language :: Python :: 3.8
Classifier: Programming Language :: Python :: 3.9
Classifier: Programming Language :: Python :: 3.10
Classifier: Programming Language :: Python :: 3.11
Requires-Python: >=3.8
License-File: LICENSE
Requires-Dist: httpx>=0.24.0
Requires-Dist: pydantic>=2.0.0
Requires-Dist: python-dotenv>=1.0.0
Provides-Extra: dev
Requires-Dist: pytest>=7.0.0; extra == "dev"
Requires-Dist: pytest-asyncio>=0.21.0; extra == "dev"
Requires-Dist: black>=23.0.0; extra == "dev"
Requires-Dist: isort>=5.12.0; extra == "dev"
Requires-Dist: mypy>=1.0.0; extra == "dev"
Dynamic: author
Dynamic: home-page
Dynamic: license-file
Dynamic: requires-python
